maestro_compose/__init__.py
maestro_compose/__main__.py
maestro_compose/commands.py
maestro_compose/models.py
maestro_compose-0.3.9.dist-info/METADATA
maestro_compose-0.3.9.dist-info/WHEEL
maestro_compose-0.3.9.dist-info/entry_points.txt
maestro_compose-0.3.9.dist-info/RECORD
