Metadata-Version: 2.1
Name: maestro-compose
Version: 0.3.9
Summary: A simple command line tool for managing Docker Compose stacks using tags and other metadata.
Home-page: https://github.com/nschenone/maestro-compose
License: MIT
Author: Nick Schenone
Author-email: nschenone16@gmail.com
Requires-Python: >=3.9,<4.0
Classifier: License :: OSI Approved :: MIT License
Classifier: Programming Language :: Python :: 3
Classifier: Programming Language :: Python :: 3.9
Classifier: Programming Language :: Python :: 3.10
Classifier: Programming Language :: Python :: 3.11
Classifier: Programming Language :: Python :: 3.12
Requires-Dist: ansible (==8.7.0)
Requires-Dist: ansible-runner (>=2.4.0,<3.0.0)
Requires-Dist: click (>=8.1.7,<9.0.0)
Requires-Dist: colorama (>=0.4.6,<0.5.0)
Requires-Dist: cookiecutter (>=2.6.0,<3.0.0)
Requires-Dist: loguru (>=0.7.2,<0.8.0)
Requires-Dist: pandas (>=2.2.2,<3.0.0)
Requires-Dist: pydantic (>=2.7.1,<3.0.0)
Requires-Dist: pyyaml (>=6.0.1,<7.0.0)
Requires-Dist: requests (==2.31.0)
Requires-Dist: tabulate (>=0.9.0,<0.10.0)
Project-URL: Repository, https://github.com/nschenone/maestro-compose
